[
    {
        "name": "Alice",
        "age": 30
    },
    {
        "name": "Bob",
        "age": 28
    },
    {
        "name": "Eve",
        "age": 27
    },
    {
        "name": "Liam",
        "age": 32
    },
    {
        "name": "Emma",
        "age": 29
    },
    {
        "name": "Oliver",
        "age": 31
    },
    {
        "name": "Sophia",
        "age": 26
    },
    {
        "name": "William",
        "age": 33
    },
    {
        "name": "Ava",
        "age": 28
    },
    {
        "name": "James",
        "age": 30
    },
    {
        "name": "Mia",
        "age": 27
    },
    {
        "name": "Ethan",
        "age": 29
    },
    {
        "name": "Charlotte",
        "age": 31
    },
    {
        "name": "Noah",
        "age": 26
    },
    {
        "name": "Amelia",
        "age": 32
    },
    {
        "name": "Michael",
        "age": 28
    },
    {
        "name": "Isabella",
        "age": 30
    },
    {
        "name": "Alexander",
        "age": 27
    },
    {
        "name": "Sophie",
        "age": 33
    },
    {
        "name": "Benjamin",
        "age": 28
    }
]